picnic_bio/__init__.py
picnic_bio/exceptions.py
picnic_bio/main.py
picnic_bio/stride.py
picnic_bio/features/__init__.py
picnic_bio/features/calculation_disorder.py
picnic_bio/features/goterms.py
picnic_bio/features/sequence_complexity.py
picnic_bio/features/sequence_distance.py
picnic_bio/features/sequence_structure_AF2.py
picnic_bio/files/__init__.py
picnic_bio/files/go/bp_2500_freq.txt
picnic_bio/files/go/bp_2500_freq_all.json
picnic_bio/files/go/cc_2000_freq.txt
picnic_bio/files/go/cc_2000_freq_all.json
picnic_bio/files/go/mf_2500_freq.txt
picnic_bio/files/go/mf_2500_freq_all.json
picnic_bio/files/models_llps/keys_llps_withgonocc_retrained_newgo_18.txt
picnic_bio/files/models_llps/keys_llps_withoutgocattrue_92.txt
picnic_bio/files/models_llps/modelpipe_depth6class1_id_2_llps_withgonocc_retrained_newgo18.sav
picnic_bio/files/models_llps/modelpipe_depth7class1_id_92_llps_withoutgo_24-02.sav
picnic_bio/prediction/__init__.py
picnic_bio/prediction/calculation_pipeline.py
picnic_bio/prediction/create_model.py
picnic_bio/prediction/inference_model.py
picnic_bio-1.0.1.dist-info/licenses/LICENSE
picnic_bio-1.0.1.dist-info/METADATA
picnic_bio-1.0.1.dist-info/WHEEL
picnic_bio-1.0.1.dist-info/entry_points.txt
picnic_bio-1.0.1.dist-info/top_level.txt
picnic_bio-1.0.1.dist-info/RECORD
