Metadata-Version: 2.4
Name: picnic_bio
Version: 1.0.1
Summary: PICNIC (Proteins Involved in CoNdensates In Cells) is a machine learning-based model that predicts proteins involved in biomolecular condensates.
Author-email: Anna Hadarovich <hadarovi@mpi-cbg.de>, Soumyadeep Ghosh <soumyadeep11194@gmail.com>, Maxim Scheremetjew <schereme@mpi-cbg.de>
Maintainer-email: Maxim Scheremetjew <schereme@mpi-cbg.de>
License-Expression: BSD-3-Clause
Project-URL: Source, https://git.mpi-cbg.de/tothpetroczylab/picnic
Project-URL: Documentation, https://git.mpi-cbg.de/tothpetroczylab/picnic/-/blob/main/README.md
Project-URL: Funding, https://picnic.cd-code.org/about-us
Project-URL: Homepage, https://picnic.cd-code.org/
Project-URL: Tracker, https://git.mpi-cbg.de/tothpetroczylab/picnic/-/issues
Keywords: Biomolecular condensate,Scientific Annotation Tool,condensate,machine learning
Classifier: Development Status :: 4 - Beta
Classifier: Intended Audience :: Science/Research
Classifier: Topic :: Scientific/Engineering :: Bio-Informatics
Classifier: Programming Language :: Python
Classifier: Programming Language :: Python :: 3
Classifier: Programming Language :: Python :: 3 :: Only
Classifier: Programming Language :: Python :: 3.9
Classifier: Programming Language :: Python :: 3.10
Classifier: Programming Language :: Python :: 3.11
Classifier: Programming Language :: Python :: 3.12
Classifier: Operating System :: Unix
Classifier: Operating System :: MacOS
Requires-Python: <3.13,>=3.9
License-File: LICENSE
Requires-Dist: requests~=2.32.0
Requires-Dist: catboost~=1.2.7
Requires-Dist: matplotlib~=3.9.4
Requires-Dist: pandas~=2.2.3
Requires-Dist: Bio~=1.6.2
Requires-Dist: numpy~=1.26.4
Dynamic: license-file
